calcrule_contribution_income_percentage/__init__.py
calcrule_contribution_income_percentage/admin.py
calcrule_contribution_income_percentage/apps.py
calcrule_contribution_income_percentage/calculation_rule.py
calcrule_contribution_income_percentage/config.py
calcrule_contribution_income_percentage/models.py
calcrule_contribution_income_percentage/urls.py
calcrule_contribution_income_percentage/views.py
calcrule_contribution_income_percentage/migrations/__init__.py
calcrule_contribution_income_percentage/tests/__init__.py
calcrule_contribution_income_percentage/tests/helpers.py
calcrule_contribution_income_percentage/tests/helpers_tests.py
calcrule_contribution_income_percentage/tests/test_gql.py
openimis_be_calcrule_contribution_income_percentage-1.8.1.dist-info/licenses/LICENSE
openimis_be_calcrule_contribution_income_percentage-1.8.1.dist-info/METADATA
openimis_be_calcrule_contribution_income_percentage-1.8.1.dist-info/WHEEL
openimis_be_calcrule_contribution_income_percentage-1.8.1.dist-info/top_level.txt
openimis_be_calcrule_contribution_income_percentage-1.8.1.dist-info/RECORD
